flask_gfwlist2pac
