Metadata-Version: 1.1
Name: Flask-Gfwlist2Pac
Version: 0.0.2
Summary: Flask application to generate PAC file based on gfwlist
Home-page: https://github.com/leoleozhu/flask_gfwlist2pac/
Author: leoleozhu
Author-email: leiping.zhu@gmail.com
License: MIT
Platform: any
Classifier: Environment :: Web Environment
Classifier: Intended Audience :: Developers
Classifier: License :: OSI Approved :: MIT License
Classifier: Operating System :: OS Independent
Classifier: Programming Language :: Python
Classifier: Topic :: Internet :: WWW/HTTP :: Dynamic Content
Classifier: Topic :: Software Development :: Libraries :: Python Modules
